lit/__init__.py
lit/__version__.py
lit/cli.py
lit/strings_holder.py
lit/util.py
lit/command/AddCommand.py
lit/command/BaseCommand.py
lit/command/BranchCommand.py
lit/command/CheckoutCommand.py
lit/command/CommitCommand.py
lit/command/DiffCommand.py
lit/command/InitCommand.py
lit/command/LogCommand.py
lit/command/RmCommand.py
lit/command/SettingsCommand.py
lit/command/StatusCommand.py
lit/command/__init__.py
lit/command/exception.py
lit/diff/roberteldersoftwarediff.py
lit/file/FileWorker.py
lit/file/ISerializer.py
lit/file/JSONSerializer.py
lit/file/exception.py
litvcs-0.1.dist-info/DESCRIPTION.rst
litvcs-0.1.dist-info/METADATA
litvcs-0.1.dist-info/RECORD
litvcs-0.1.dist-info/WHEEL
litvcs-0.1.dist-info/entry_points.txt
litvcs-0.1.dist-info/metadata.json
litvcs-0.1.dist-info/top_level.txt
litvcs-0.1.dist-info/zip-safe
