Metadata-Version: 2.0
Name: litvcs
Version: 0.1
Summary: The project “LIT” is a version control system.
Home-page: https://github.com/Kh-011-WebUIPython/lit-cli
Author: Maxim Krivich
Author-email: maxkrivich@gmail.com
License: MIT
Platform: UNKNOWN
Classifier: Development Status :: 4 - Beta
Classifier: Environment :: Console
Classifier: Intended Audience :: Developers
Classifier: License :: OSI Approved :: MIT License
Classifier: Operating System :: POSIX
Classifier: Operating System :: MacOS
Classifier: Operating System :: Unix
Classifier: Programming Language :: Python
Classifier: Programming Language :: Python :: 3
Classifier: Topic :: Software Development :: Libraries :: Python Modules
